shipyard_rudderstack/__init__.py
shipyard_rudderstack/cli/authtest.py
shipyard_rudderstack/cli/trigger_sync_cli.py
shipyard_rudderstack/rudderstack.py
shipyard_rudderstack-0.1.3.dist-info/METADATA
shipyard_rudderstack-0.1.3.dist-info/WHEEL
shipyard_rudderstack-0.1.3.dist-info/RECORD
